aegis_data/__init__.py
aegis_data/api/__init__.py
aegis_data/api/wows_api.py
aegis_data/database/__init__.py
aegis_data/database/abstract_db.py
aegis_data/database/database_factory.py
aegis_data/database/mongo_db.py
aegis_data/util/__init__.py
aegis_data/util/ansi_code.py
aegis_data/util/aux_functions.py
aegis_data/util/config.py
aegis_data-0.1.2.data/data/config/sample_config.json
aegis_data-0.1.2.data/data/config/sample_newstats.json
aegis_data-0.1.2.data/data/config/sample_stats.json
aegis_data-0.1.2.data/scripts/collect-wows-data.py
aegis_data-0.1.2.data/scripts/collect-wows-ids.py
aegis_data-0.1.2.dist-info/LICENSE
aegis_data-0.1.2.dist-info/METADATA
aegis_data-0.1.2.dist-info/WHEEL
aegis_data-0.1.2.dist-info/top_level.txt
aegis_data-0.1.2.dist-info/RECORD
